lassh/__init__.py
lassh/__main__.py
lassh/lassh.py
lassh/test/__init__.py
lassh/test/test_lassh.py
lassh-0.1.1.dist-info/LICENSE.txt
lassh-0.1.1.dist-info/METADATA
lassh-0.1.1.dist-info/WHEEL
lassh-0.1.1.dist-info/entry_points.txt
lassh-0.1.1.dist-info/top_level.txt
lassh-0.1.1.dist-info/RECORD
