Metadata-Version: 2.1
Name: lassh
Version: 0.1.1
Summary: An open source, MIT-licensed command line tool for managing per-project ssh configs.
Home-page: https://github.com/stevenrchun/lassh
Author: Steven Chun
Author-email: schunchicago@gmail.com
License: LICENSE.txt
Platform: UNKNOWN
Requires-Dist: Click
Requires-Dist: sshconf
Requires-Dist: setuptools
Requires-Dist: clint
Requires-Dist: pathlib
